trustocean_sdk/__init__.py
trustocean_sdk/client.py
trustocean_sdk/exception.py
trustocean_sdk/request.py
trustocean_sdk/utils.py
trustocean_sdk-1.0.1.dist-info/LICENSE
trustocean_sdk-1.0.1.dist-info/METADATA
trustocean_sdk-1.0.1.dist-info/WHEEL
trustocean_sdk-1.0.1.dist-info/top_level.txt
trustocean_sdk-1.0.1.dist-info/RECORD
