Metadata-Version: 2.1
Name: trustocean-sdk
Version: 1.0.1
Summary: A SDK package of TrustOcean Limited SSL API
Home-page: https://github.com/londry/TRUSTOCEAN-SDK-PYTHON
Author: TrustOcean Limited
Author-email: jasonlong@qiaokr.com
License: UNKNOWN
Platform: UNKNOWN
Classifier: Programming Language :: Python :: 3
Classifier: License :: OSI Approved :: MIT License
Classifier: Operating System :: OS Independent
Requires-Python: >=3.6
